{
  "generated_at": "2026-05-21T09:40:53.245514",
  "asof_date": "2026-05-20 00:00:00",
  "data": {
    "total_bars": 375149,
    "unique_symbols": 501,
    "date_range": {
      "start": "2023-05-22 00:00:00",
      "end": "2026-05-20 00:00:00"
    }
  },
  "features": {
    "total_rows": 375149,
    "unique_symbols": 501
  },
  "top10": {
    "generated": true,
    "count": 10
  },
  "update_results": {
    "skipped": true
  },
  "coverage": {
    "asof_date_symbols": 498,
    "asof_date_rate": 0.9979959919839679
  }
}