{
  "generated_at": "2026-02-13T07:02:58.478961",
  "asof_date": "2026-02-12 00:00:00",
  "data": {
    "total_bars": 375544,
    "unique_symbols": 502,
    "date_range": {
      "start": "2023-02-14 00:00:00",
      "end": "2026-02-12 00:00:00"
    }
  },
  "features": {
    "total_rows": 375544,
    "unique_symbols": 502
  },
  "top10": {
    "generated": true,
    "count": 10
  },
  "update_results": {
    "skipped": true
  },
  "coverage": {
    "asof_date_symbols": 500,
    "asof_date_rate": 0.998003992015968
  }
}